cohere_ui/__init__.py
cohere_ui/beamline_preprocess.py
cohere_ui/beamline_visualization.py
cohere_ui/cohere_gui.py
cohere_ui/copy_setup.py
cohere_ui/create_aps34idc_experiment.py
cohere_ui/everything.py
cohere_ui/run_reconstruction.py
cohere_ui/simple_phasing.py
cohere_ui/standard_preprocess.py
cohere_ui/api/__init__.py
cohere_ui/api/auto_data.py
cohere_ui/api/balancer.py
cohere_ui/api/common.py
cohere_ui/api/convertconfig.py
cohere_ui/api/host_utils.py
cohere_ui/api/mpi_cmd.py
cohere_ui/api/multipeak.py
cohere_ui/api/postprocess_utils.py
cohere_ui/api/reconstruction_ga.py
cohere_ui/api/reconstruction_populous.py
cohere_ui/api/reconstruction_populous_ga.py
cohere_ui/api/symdata.py
cohere_ui/api/te_preprocess.py
cohere_ui/api/te_rec.py
cohere_ui/api/view_reconstruction.py
cohere_ui-4.4.0.dist-info/licenses/LICENSE
cohere_ui-4.4.0.dist-info/METADATA
cohere_ui-4.4.0.dist-info/WHEEL
cohere_ui-4.4.0.dist-info/entry_points.txt
cohere_ui-4.4.0.dist-info/top_level.txt
cohere_ui-4.4.0.dist-info/RECORD
