Metadata-Version: 2.4
Name: cohere_ui
Version: 4.4.0
Summary: cohere scripts
Author-email: Barbara Frosik <bfrosik@anl.gov>, Ross Harder <rharder@anl.gov>
License: Copyright © 2019, UChicago Argonne, LLC
Project-URL: Homepage, https://github.com/AdvancedPhotonSource/cohere-ui
Classifier: Programming Language :: Python :: 3
Classifier: Operating System :: OS Independent
Requires-Python: >=3.11
License-File: LICENSE
Requires-Dist: pyqt5
Requires-Dist: scikit-image
Requires-Dist: xrayutilities
Requires-Dist: pyvista
Requires-Dist: scipy==1.14.1
Requires-Dist: notebook
Requires-Dist: gputil
Dynamic: license-file
